H2GB/__init__.py
H2GB/agg_runs.py
H2GB/calcHomophily.py
H2GB/finetuning.py
H2GB/logger.py
H2GB/main.py
H2GB/metric_wrapper.py
H2GB/metrics_ogb.py
H2GB/timer.py
H2GB/utils.py
H2GB/act/__init__.py
H2GB/act/example.py
H2GB/config/__init__.py
H2GB/config/dataset_config.py
H2GB/config/defaults_config.py
H2GB/config/gt_config.py
H2GB/config/optimizers_config.py
H2GB/config/posenc_config.py
H2GB/config/pretrained_config.py
H2GB/config/split_config.py
H2GB/config/wandb_config.py
H2GB/datasets/__init__.py
H2GB/datasets/ieee_cis_dataset.py
H2GB/datasets/mag_dataset.py
H2GB/datasets/oag_dataset.py
H2GB/datasets/pdns_dataset.py
H2GB/datasets/pokec_dataset.py
H2GB/datasets/rcdd_dataset.py
H2GB/datasets/utils.py
H2GB/encoder/__init__.py
H2GB/encoder/composed_encoders.py
H2GB/encoder/graphormer_encoder.py
H2GB/encoder/hetero_bias_encoder.py
H2GB/encoder/hetero_distance_encoder.py
H2GB/encoder/hetero_embed_encoder.py
H2GB/encoder/hetero_gnn_encoder.py
H2GB/encoder/hetero_label_encoder.py
H2GB/encoder/hetero_pos_encoder.py
H2GB/encoder/hetero_raw_encoder.py
H2GB/encoder/homo_gnn_encoder.py
H2GB/encoder/kernel_pos_encoder.py
H2GB/encoder/laplace_pos_encoder.py
H2GB/encoder/raw_encoder.py
H2GB/encoder/voc_superpixels_encoder.py
H2GB/graphgym/__init__.py
H2GB/graphgym/checkpoint.py
H2GB/graphgym/cmd_args.py
H2GB/graphgym/config.py
H2GB/graphgym/init.py
H2GB/graphgym/loader.py
H2GB/graphgym/loader_deepsnap.py
H2GB/graphgym/logger.py
H2GB/graphgym/loss.py
H2GB/graphgym/model_builder.py
H2GB/graphgym/model_builder_deepsnap.py
H2GB/graphgym/optimizer.py
H2GB/graphgym/register.py
H2GB/graphgym/train.py
H2GB/graphgym/train_deepsnap.py
H2GB/graphgym/contrib/__init__.py
H2GB/graphgym/contrib/act/__init__.py
H2GB/graphgym/contrib/act/example.py
H2GB/graphgym/contrib/config/__init__.py
H2GB/graphgym/contrib/config/example.py
H2GB/graphgym/contrib/feature_augment/__init__.py
H2GB/graphgym/contrib/feature_augment/example.py
H2GB/graphgym/contrib/feature_encoder/__init__.py
H2GB-0.1.0.dist-info/LICENSE
H2GB-0.1.0.dist-info/METADATA
H2GB-0.1.0.dist-info/WHEEL
H2GB-0.1.0.dist-info/entry_points.txt
H2GB-0.1.0.dist-info/top_level.txt
H2GB-0.1.0.dist-info/RECORD
