Metadata-Version: 2.1
Name: H2GB
Version: 0.1.0
Summary: A graph benchmark library for heterophilic and heterogeneous graphs
Home-page: https://github.com/junhongmit/H2GB
Author: Junhong Lin
Author-email: junhong@mit.edu
Classifier: Programming Language :: Python :: 3
Classifier: License :: OSI Approved :: MIT License
Classifier: Operating System :: OS Independent
Requires-Python: >=3.6
License-File: LICENSE
Requires-Dist: torch
Requires-Dist: torch-geometric
Requires-Dist: torch-sparse
Requires-Dist: torch-scatter
Requires-Dist: ogb
Requires-Dist: yacs
Requires-Dist: dill
Requires-Dist: torchmetrics
Requires-Dist: wandb
Requires-Dist: seaborn
Requires-Dist: gdown
Requires-Dist: pytorch-lightning
Requires-Dist: datatable
Requires-Dist: prettytable
